./.gitignore
./PKG-INFO
./README.md
./README_CN.md
./build_executable.bat
./config.json
./config_manager.py
./lang_manager.py
./main.py
./pyproject.toml
./test_ssl.py
./.github/workflows/build.yml
./client/mcp_client.py
./client/mcp_client_stdio.py
./doc/2025-06-27 优化基于pyqt插件的功能体验.md
./doc/image-1.png
./doc/image-2.png
./doc/image.png
./docs/github_actions_guide.md
./locales/en_US.json
./locales/zh_CN.json
./requirements/requirements-all.txt
./requirements/requirements-base.txt
./requirements/requirements-pyqt.txt
./requirements/requirements-web.txt
./ui/test_ui.py
./ui/ui.py
./ui/ui_cli.py
./ui/ui_dpg.py
./ui/ui_psg.py
./ui/ui_pyqt.py
./ui/ui_web.py
./web_templates/base.html
./web_templates/index.html
./web_templates/info.html
./web_templates/select.html
locales/en_US.json
locales/zh_CN.json
ui/test_ui.py
ui/ui.py
ui/ui_cli.py
ui/ui_dpg.py
ui/ui_psg.py
ui/ui_pyqt.py
ui/ui_web.py
iflow_mcp_interaction_mcp-0.1.0.dist-info/METADATA
iflow_mcp_interaction_mcp-0.1.0.dist-info/WHEEL
iflow_mcp_interaction_mcp-0.1.0.dist-info/entry_points.txt
iflow_mcp_interaction_mcp-0.1.0.dist-info/RECORD
