Metadata-Version: 2.4
Name: iflow-mcp_interaction-mcp
Version: 0.1.0
Summary: MCP Interactive Service for Cursor and Windsurf
License: MIT
Requires-Python: >=3.8
Requires-Dist: fastmcp>=2.3.0
Requires-Dist: httpx>=0.24.0
Requires-Dist: psutil>=5.9.0
Requires-Dist: python-dotenv>=1.1.0
Requires-Dist: typer>=0.15.0
Provides-Extra: all
Requires-Dist: flask-socketio>=5.0.0; extra == 'all'
Requires-Dist: flask>=2.0.0; extra == 'all'
Requires-Dist: pyqt5>=5.15.0; extra == 'all'
Provides-Extra: pyqt
Requires-Dist: pyqt5>=5.15.0; extra == 'pyqt'
Provides-Extra: tkinter
Provides-Extra: web
Requires-Dist: flask-socketio>=5.0.0; extra == 'web'
Requires-Dist: flask>=2.0.0; extra == 'web'
